vayu/TheilSen.py
vayu/__init__.py
vayu/_version.py
vayu/calendarPlot.py
vayu/googleMaps.py
vayu/interactiveChoroplethPlot.py
vayu/interpolPlot.py
vayu/linearRelation.py
vayu/polarFreq.py
vayu/pollutionRose.py
vayu/scatterPlot.py
vayu/selectByDate.py
vayu/smoothTrend.py
vayu/summaryPlot.py
vayu/timeInteractiveScatterPlot.py
vayu/timePlot.py
vayu/timeProp.py
vayu/timeVariation.py
vayu/trendLevel.py
vayu/utils.py
vayu-0.0.214.dist-info/LICENSE.txt
vayu-0.0.214.dist-info/METADATA
vayu-0.0.214.dist-info/WHEEL
vayu-0.0.214.dist-info/top_level.txt
vayu-0.0.214.dist-info/RECORD
